[
  {
    "id": 0,
    "data": "Age",
    "pieOptions":
      {
        "title": "Age distribution of users",
        "colors": ["#FFCCBC", "#FFAB91", "#FF8A65","#FF7043", "#FF5722", "#F4511E", "#E64A19", "#D84315", "#BF360C"],
        "is3D": false
      },
    "barOptions":
      {
        "title": "Age distribution of users",
        "colors": ["#FF5722", "#E64A19", "#BF360C", "#FFCCBC", "#FF8A65"]
      }
  },
  {
    "id": 1,
    "data": "Height",
    "pieOptions":
      {
        "title": "Height distribution of users",
        "colors": ["#FFCCBC", "#FFAB91", "#FF8A65", "#FF7043", "#FF5722", "#F4511E", "#E64A19", "#D84315", "#BF360C"],
        "is3D": false
      },
    "barOptions":
      {
        "title": "Height distribution of users",
        "colors": ["#FF5722", "#E64A19", "#BF360C", "#FFCCBC", "#FF8A65"]
      }
  },
  {
    "id": 2,
    "data": "Weight",
    "pieOptions":
      {
        "title": "Body Mass Index distribution of users",
        "colors": ["#FFCCBC", "#FFAB91", "#FF8A65", "#FF7043", "#FF5722", "#F4511E", "#E64A19", "#D84315", "#BF360C"],
        "is3D": false
      },
    "barOptions":
      {
        "title": "Body Mass Index distribution of users",
        "colors": ["#FF5722", "#E64A19", "#BF360C", "#FFCCBC", "#FF8A65"]
      }
  },
  {
    "id": 3,
    "data": "Education",
    "pieOptions":
      {
        "title": "Education level distribution of users",
        "colors": ["#FFCCBC", "#FFAB91", "#FF8A65", "#FF7043", "#FF5722", "#F4511E", "#E64A19", "#D84315", "#BF360C"],
        "is3D": false
      },
    "barOptions":
      {
        "title": "Education level distribution of users",
        "colors": ["#FF5722", "#E64A19", "#BF360C", "#FFCCBC", "#FF8A65"]
      }
  }
]
